boxtodocx/__init__.py
boxtodocx/__main__.py
boxtodocx/cli.py
boxtodocx/converter.py
boxtodocx/handlers/Readme.md
boxtodocx/handlers/__init__.py
boxtodocx/handlers/docx_handler.py
boxtodocx/handlers/html_handler.py
boxtodocx/mappers/Readme.md
boxtodocx/mappers/__init__.py
boxtodocx/mappers/html_mapper.py
boxtodocx/utils/Readme.md
boxtodocx/utils/__init__.py
boxtodocx/utils/logger.py
boxtodocx-1.0.0.dist-info/METADATA
boxtodocx-1.0.0.dist-info/WHEEL
boxtodocx-1.0.0.dist-info/entry_points.txt
boxtodocx-1.0.0.dist-info/top_level.txt
boxtodocx-1.0.0.dist-info/RECORD
