Metadata-Version: 2.1
Name: boxtodocx
Version: 1.0.0
Summary: Convert Box Notes to Microsoft Word (docx) documents
Home-page: https://github.com/ujjwal-ibm/boxtodocx
Author: Ujjwal Kumar
Author-email: ramuklawjju12321@gmail.com
Project-URL: Bug Tracker, https://github.com/ujjwal-ibm/boxtodocx/issues
Project-URL: Documentation, https://github.com/ujjwal-ibm/boxtodocx
Classifier: Development Status :: 5 - Production/Stable
Classifier: Intended Audience :: Developers
Classifier: License :: OSI Approved :: MIT License
Classifier: Operating System :: OS Independent
Classifier: Programming Language :: Python :: 3
Classifier: Programming Language :: Python :: 3.8
Classifier: Programming Language :: Python :: 3.9
Classifier: Programming Language :: Python :: 3.10
Classifier: Programming Language :: Python :: 3.11
Classifier: Topic :: Office/Business
Classifier: Topic :: Text Processing
Requires-Python: >=3.8
Requires-Dist: beautifulsoup4>=4.9.3
Requires-Dist: python-docx>=0.8.11
Requires-Dist: requests>=2.25.1
Requires-Dist: click>=8.0.0
Requires-Dist: typing-extensions>=4.0.0
Requires-Dist: colorlog>=6.7.0
